geosimilarity/__init__.py
geosimilarity/chamfer.py
geosimilarity/hausdorff.py
geosimilarity/mae.py
geosimilarity/max_abs_error.py
geosimilarity/max_sq_error.py
geosimilarity/mse.py
geosimilarity/smooth_hausdorff.py
geosimilarity/smooth_max_sq_error.py
geosimilarity/usdf.py
testing/__init__.py
testing/shapes.py
testing/testing.py
testing/utils.py
geosimilarity-0.0.1.dist-info/LICENSE
geosimilarity-0.0.1.dist-info/METADATA
geosimilarity-0.0.1.dist-info/WHEEL
geosimilarity-0.0.1.dist-info/top_level.txt
geosimilarity-0.0.1.dist-info/RECORD
