Metadata-Version: 2.1
Name: geosimilarity
Version: 0.0.1
Summary: Differentiable curve and surface similarity measures.
Home-page: https://github.com/atharvaaalok/geosimilarity
Author: Atharva Aalok
Author-email: atharvaaalok@gmail.com
License: MIT
Keywords: geosimilarity,geometry,neural networks,loss functions,machine learning,deep learning,optimization,curve fitting,pytorch,autograd,similarity measures,surfaces,curves
Platform: UNKNOWN
License-File: LICENSE
Requires-Dist: matplotlib==3.10.0
Requires-Dist: numpy==2.2.3
Requires-Dist: setuptools==57.4.0
Requires-Dist: svg.path==6.3
Requires-Dist: torch==2.5.1
Requires-Dist: typing-extensions==4.12.2
